[
  {
    "id": 111381031722126435,
    "created_at": "2023-11-09T14:21:08.615000+00:00",
    "sensitive": false,
    "visibility": "public",
    "language": "cs",
    "uri": "https://mastodonczech.cz/users/honzajavorek/statuses/111381031722126435",
    "url": "https://mastodonczech.cz/@honzajavorek/111381031722126435",
    "replies_count": 1,
    "favourited": false,
    "reblogged": false,
    "muted": false,
    "bookmarked": false,
    "pinned": false,
    "content": "<p>Chris vysvětluje, kam se posouvá svět dokumentace. React komponenty přímo v textu. Setkali jste se už s nějakými takovými dynamickými prvky? Používáte? <a href=\"https://www.youtube.com/watch?v=9PMu3i4-RFk\" target=\"_blank\" rel=\"nofollow noopener noreferrer\" translate=\"no\"><span class=\"invisible\">https://www.</span><span class=\"ellipsis\">youtube.com/watch?v=9PMu3i4-RF</span><span class=\"invisible\">k</span></a> <a href=\"https://mastodonczech.cz/tags/links\" class=\"mention hashtag\" rel=\"tag\">#<span>links</span></a></p>",
    "tags": [
      {
        "name": "links",
        "url": "https://mastodonczech.cz/tags/links"
      }
    ],
    "card": {
      "url": "https://www.youtube.com/watch?v=9PMu3i4-RFk",
      "title": "Is the future of documentation dynamic?",
      "type": "video",
      "author_name": "Chris Chinchilla",
      "author_url": "https://www.youtube.com/@ChrisChinchillaWatch",
      "provider_name": "YouTube",
      "provider_url": "https://www.youtube.com/",
      "html": "<iframe width=\"200\" height=\"113\" src=\"https://www.youtube.com/embed/9PMu3i4-RFk?feature=oembed\" frameborder=\"0\" allowfullscreen=\"\" sandbox=\"allow-scripts allow-same-origin allow-popups allow-popups-to-escape-sandbox allow-forms\"></iframe>",
      "width": 200,
      "height": 113,
      "image": "https://mastodonczech.cz/system/cache/preview_cards/images/002/539/974/original/55c04cc40fd33f53.jpg",
      "blurhash": "UeI5Vv9FtRxv%2aeRjof00xuV@RiNGj[s:WB"
    }
  },
  {
    "id": 111373715339299636,
    "created_at": "2023-11-08T07:20:29.472000+00:00",
    "sensitive": false,
    "visibility": "public",
    "language": "cs",
    "uri": "https://mastodonczech.cz/users/honzajavorek/statuses/111373715339299636",
    "url": "https://mastodonczech.cz/@honzajavorek/111373715339299636",
    "favourites_count": 2,
    "favourited": false,
    "reblogged": false,
    "muted": false,
    "bookmarked": false,
    "pinned": false,
    "content": "<p>Zajímavý přehled, byť mi tam trochu chybí zmínka o českém programu Kosmo 😉 <a href=\"https://www.voxpot.cz/velmoci-se-pretahuji-o-mesic-planuji-na-nem-zakladny-i-trenink-astronautu-pro-cestu-k-marsu/\" target=\"_blank\" rel=\"nofollow noopener noreferrer\" translate=\"no\"><span class=\"invisible\">https://www.</span><span class=\"ellipsis\">voxpot.cz/velmoci-se-pretahuji</span><span class=\"invisible\">-o-mesic-planuji-na-nem-zakladny-i-trenink-astronautu-pro-cestu-k-marsu/</span></a> <a href=\"https://mastodonczech.cz/tags/links\" class=\"mention hashtag\" rel=\"tag\">#<span>links</span></a></p>",
    "tags": [
      {
        "name": "links",
        "url": "https://mastodonczech.cz/tags/links"
      }
    ],
    "card": {
      "url": "https://www.voxpot.cz/velmoci-se-pretahuji-o-mesic-planuji-na-nem-zakladny-i-trenink-astronautu-pro-cestu-k-marsu/",
      "title": "Velmoci se přetahují o Měsíc. Plánují na něm základny i trénink astronautů pro cestu k Marsu - VOXPOT",
      "description": "Světové velmoci i řada dalších hráčů míří na Měsíc. Ten se tak stane středobodem dobývání vesmíru v příštím desetiletí. A možná mu to vydrží i déle. Ale proč? Co je na něm tak mimořádného právě teď, ve 20. letech 21. století?",
      "language": "cs",
      "type": "link",
      "provider_name": "VOXPOT",
      "width": 2000,
      "height": 1005,
      "image": "https://mastodonczech.cz/system/cache/preview_cards/images/002/510/792/original/be0512d0f0b99134.jpg",
      "blurhash": "UWE2E~X9E1E10gslt6kCM{WBxu%2-pbbWAM|",
      "published_at": "2023-11-07T04:26:45+00:00"
    }
  },
  {
    "id": 111336130153780072,
    "created_at": "2023-11-01T16:02:05.054000+00:00",
    "sensitive": false,
    "visibility": "public",
    "language": "cs",
    "uri": "https://mastodonczech.cz/users/honzajavorek/statuses/111336130153780072",
    "url": "https://mastodonczech.cz/@honzajavorek/111336130153780072",
    "favourites_count": 2,
    "favourited": false,
    "reblogged": false,
    "muted": false,
    "bookmarked": false,
    "pinned": false,
    "content": "<p>Kašpárek: „Do jaké míry si mohu zařídit život podle sebe? Urvat si, co chci, a „děcka nazdar, prostě jste samostatný?“ Do jaké míry a komu se vlastně za svoje skutky a životní volby zodpovídám?“ <a href=\"https://www.seznamzpravy.cz/clanek/kultura-muzi-se-po-ctyricitce-nekam-ztrati-rika-spisovatel-michal-kasparek-239175\" target=\"_blank\" rel=\"nofollow noopener noreferrer\" translate=\"no\"><span class=\"invisible\">https://www.</span><span class=\"ellipsis\">seznamzpravy.cz/clanek/kultura</span><span class=\"invisible\">-muzi-se-po-ctyricitce-nekam-ztrati-rika-spisovatel-michal-kasparek-239175</span></a> <a href=\"https://mastodonczech.cz/tags/links\" class=\"mention hashtag\" rel=\"tag\">#<span>links</span></a></p>",
    "tags": [
      {
        "name": "links",
        "url": "https://mastodonczech.cz/tags/links"
      }
    ],
    "card": {
      "url": "https://www.seznamzpravy.cz/clanek/kultura-muzi-se-po-ctyricitce-nekam-ztrati-rika-spisovatel-michal-kasparek-239175",
      "title": "„Muži se po čtyřicítce někam ztratí,“ říká spisovatel Michal Kašpárek",
      "description": "Spisovatel a novinář Michal Kašpárek napsal knihu, která se na svět chce dívat s odstupem geologické epochy. Zkoumá v ní mezigenerační vztahy, ale i stárnoucí muže. ",
      "language": "cs",
      "type": "link",
      "author_name": "Jonáš Zbořil",
      "provider_name": "Seznam Zprávy",
      "width": 1200,
      "height": 674,
      "image": "https://mastodonczech.cz/system/cache/preview_cards/images/002/452/416/original/a0cae32bb8c12079.jpeg",
      "blurhash": "UICYzRM|0|R%tQWBoMofcEazVYoKsna|kCs:",
      "published_at": "2023-11-01T12:30:00+00:00"
    }
  },
  {
    "id": 111335922854863361,
    "created_at": "2023-11-01T15:09:21.925000+00:00",
    "sensitive": false,
    "visibility": "public",
    "language": "cs",
    "uri": "https://mastodonczech.cz/users/honzajavorek/statuses/111335922854863361",
    "url": "https://mastodonczech.cz/@honzajavorek/111335922854863361",
    "favourited": false,
    "reblogged": false,
    "muted": false,
    "bookmarked": false,
    "pinned": false,
    "content": "<p>Chystá se kompletní rekonstrukce Hlaváku a přednádražního prostoru v Praze <a href=\"https://overcast.fm/+6eCRwbHqw\" target=\"_blank\" rel=\"nofollow noopener noreferrer\" translate=\"no\"><span class=\"invisible\">https://</span><span class=\"\">overcast.fm/+6eCRwbHqw</span><span class=\"invisible\"></span></a> <a href=\"https://mastodonczech.cz/tags/links\" class=\"mention hashtag\" rel=\"tag\">#<span>links</span></a></p>",
    "tags": [
      {
        "name": "links",
        "url": "https://mastodonczech.cz/tags/links"
      }
    ],
    "card": {
      "url": "https://overcast.fm/+6eCRwbHqw",
      "title": "Jak bude vypadat Hlavní nádraží? Poslechněte si, co s nim mají investoři v plánu — Město",
      "language": "en",
      "type": "video",
      "html": "<iframe src=\"https://overcast.fm/podcasts/episode_card/4114411637382828?t=0\" width=\"290\" height=\"58\" allowfullscreen=\"allowfullscreen\" scrolling=\"no\" frameborder=\"0\" sandbox=\"allow-scripts allow-same-origin allow-popups allow-popups-to-escape-sandbox allow-forms\"></iframe>",
      "width": 290,
      "height": 58,
      "image": "https://mastodonczech.cz/system/cache/preview_cards/images/002/454/024/original/a4971b7e6da1de98.jpeg",
      "embed_url": "https://www.buzzsprout.com/2007031/13879569-jak-bude-vypadat-hlavni-nadrazi-poslechnete-si-co-s-nim-maji-investori-v-planu.mp3#t=0",
      "blurhash": "USKVU6xZ.mxuLNk9tlt7ItkCIARjWFofwcae"
    }
  },
  {
    "id": 111305361003489488,
    "created_at": "2023-10-27T05:37:05.078000+00:00",
    "sensitive": false,
    "visibility": "public",
    "language": "cs",
    "uri": "https://mastodonczech.cz/users/honzajavorek/statuses/111305361003489488",
    "url": "https://mastodonczech.cz/@honzajavorek/111305361003489488",
    "edited_at": "2023-10-27T16:49:01.090000+00:00",
    "favourited": false,
    "reblogged": false,
    "muted": false,
    "bookmarked": false,
    "pinned": false,
    "content": "<p>„Lame, who in 2019 was assembling car filters in a factory outside Turin, now has more than 240 million social media followers and has scored lucrative partnerships with Hugo Boss, State Farm, and Middle East bank QNB.“ Žebříček nejbohatších tvůrců. Kolik jich znáte? <a href=\"https://www.forbes.com/sites/stevenbertoni/2023/09/26/top-creators-2023/\" target=\"_blank\" rel=\"nofollow noopener noreferrer\" translate=\"no\"><span class=\"invisible\">https://www.</span><span class=\"ellipsis\">forbes.com/sites/stevenbertoni</span><span class=\"invisible\">/2023/09/26/top-creators-2023/</span></a> <a href=\"https://mastodonczech.cz/tags/links\" class=\"mention hashtag\" rel=\"tag\">#<span>links</span></a></p>",
    "tags": [
      {
        "name": "links",
        "url": "https://mastodonczech.cz/tags/links"
      }
    ],
    "card": {
      "url": "https://www.forbes.com/sites/stevenbertoni/2023/09/26/top-creators-2023/",
      "title": "Top Creators 2023",
      "description": "The Social media stars who are making millions in the Creator across Instagram, TikTok, YouTube, Spotify and Twitch turning followers into fortunes.",
      "language": "en",
      "type": "link",
      "author_name": "Steven Bertoni",
      "author_url": "https://www.forbes.com/sites/stevenbertoni/",
      "provider_name": "Forbes",
      "width": 1600,
      "height": 900,
      "image": "https://mastodonczech.cz/system/cache/preview_cards/images/002/066/669/original/dcd770fe804d39f9.jpg",
      "blurhash": "UGFY$2IU00IU_3xuIUofIU%MIU%Mxut7M{of",
      "published_at": "2023-09-26T10:30:00+00:00"
    }
  },
  {
    "id": 111302591404421622,
    "created_at": "2023-10-26T17:52:44.351000+00:00",
    "sensitive": false,
    "visibility": "public",
    "language": "cs",
    "uri": "https://mastodonczech.cz/users/honzajavorek/statuses/111302591404421622",
    "url": "https://mastodonczech.cz/@honzajavorek/111302591404421622",
    "favourited": false,
    "reblogged": false,
    "muted": false,
    "bookmarked": false,
    "pinned": false,
    "content": "<p>Lanovka! Pěkný. <a href=\"https://www.youtube.com/watch?v=35AETxkbxPw&amp;t=1s\" target=\"_blank\" rel=\"nofollow noopener noreferrer\" translate=\"no\"><span class=\"invisible\">https://www.</span><span class=\"ellipsis\">youtube.com/watch?v=35AETxkbxP</span><span class=\"invisible\">w&amp;t=1s</span></a> <a href=\"https://mastodonczech.cz/tags/links\" class=\"mention hashtag\" rel=\"tag\">#<span>links</span></a></p>",
    "tags": [
      {
        "name": "links",
        "url": "https://mastodonczech.cz/tags/links"
      }
    ],
    "card": {
      "url": "https://www.youtube.com/watch?v=35AETxkbxPw&t=1s",
      "title": "Jak bude vypadat plánovaná lanovka Podbaba – Troja – Bohnice?",
      "type": "video",
      "author_name": "Dopravní podnik hl. m. Prahy, akciová společnost",
      "author_url": "https://www.youtube.com/@dppoficialni",
      "provider_name": "YouTube",
      "provider_url": "https://www.youtube.com/",
      "html": "<iframe width=\"200\" height=\"113\" src=\"https://www.youtube.com/embed/35AETxkbxPw?start=1&amp;feature=oembed\" frameborder=\"0\" allowfullscreen=\"\" sandbox=\"allow-scripts allow-same-origin allow-popups allow-popups-to-escape-sandbox allow-forms\"></iframe>",
      "width": 200,
      "height": 113,
      "image": "https://mastodonczech.cz/system/cache/preview_cards/images/002/392/605/original/4da2fccec365ae0f.jpg",
      "blurhash": "UWD,o_IA-=tR.TjFtRozD%ofRjV@DNoyM_V@"
    }
  },
  {
    "id": 111300181074987979,
    "created_at": "2023-10-26T07:39:45.642000+00:00",
    "sensitive": false,
    "visibility": "public",
    "language": "cs",
    "uri": "https://mastodonczech.cz/users/honzajavorek/statuses/111300181074987979",
    "url": "https://mastodonczech.cz/@honzajavorek/111300181074987979",
    "favourited": false,
    "reblogged": false,
    "muted": false,
    "bookmarked": false,
    "pinned": false,
    "content": "<p>Hned několik zajímavých postřehů o vztahu předplatného, pirátství nebo reklam. „I’ve always thought of media bootlegging as a form of negotiation. It’s like ad hoc collective bargaining between users and the corporations that set the prices and define the experience of consuming the media.“ „…most articles from most publishers in Apple News are lousy with huge ugly ads, breaking up each article every few paragraphs“ <a href=\"https://daringfireball.net/2023/10/apple_again_hikes_prices_for_services\" target=\"_blank\" rel=\"nofollow noopener noreferrer\" translate=\"no\"><span class=\"invisible\">https://</span><span class=\"ellipsis\">daringfireball.net/2023/10/app</span><span class=\"invisible\">le_again_hikes_prices_for_services</span></a> <a href=\"https://mastodonczech.cz/tags/links\" class=\"mention hashtag\" rel=\"tag\">#<span>links</span></a></p>",
    "tags": [
      {
        "name": "links",
        "url": "https://mastodonczech.cz/tags/links"
      }
    ],
    "card": {
      "url": "https://daringfireball.net/2023/10/apple_again_hikes_prices_for_services",
      "title": "Apple Again Hikes Prices for Its Media Services",
      "description": "Of the three component services whose standalone prices went up, TV+ and Arcade seem justified. News+, however, does not.",
      "language": "en",
      "type": "link",
      "provider_name": "Daring Fireball",
      "width": 1500,
      "height": 500,
      "image": "https://mastodonczech.cz/system/cache/preview_cards/images/002/381/977/original/5cb6a5d351c46542.png",
      "blurhash": "U08h2wj[00j[offQfQfQ00fQ~qj[offQayfQ"
    }
  },
  {
    "id": 111294465098686174,
    "created_at": "2023-10-25T07:26:06.790000+00:00",
    "sensitive": false,
    "visibility": "public",
    "language": "cs",
    "uri": "https://mastodonczech.cz/users/honzajavorek/statuses/111294465098686174",
    "url": "https://mastodonczech.cz/@honzajavorek/111294465098686174",
    "favourites_count": 2,
    "favourited": false,
    "reblogged": false,
    "muted": false,
    "bookmarked": false,
    "pinned": false,
    "content": "<p>Jak se do budoucna změní klima zrovna v Česku? <a href=\"https://www.voxpot.cz/cistejsi-lodni-palivo-el-nino-erupce-i-ceska-anomalie-to-vse-ovlivnilo-necekany-rust-teplot/\" target=\"_blank\" rel=\"nofollow noopener noreferrer\" translate=\"no\"><span class=\"invisible\">https://www.</span><span class=\"ellipsis\">voxpot.cz/cistejsi-lodni-paliv</span><span class=\"invisible\">o-el-nino-erupce-i-ceska-anomalie-to-vse-ovlivnilo-necekany-rust-teplot/</span></a> <a href=\"https://mastodonczech.cz/tags/links\" class=\"mention hashtag\" rel=\"tag\">#<span>links</span></a></p>",
    "tags": [
      {
        "name": "links",
        "url": "https://mastodonczech.cz/tags/links"
      }
    ],
    "card": {
      "url": "https://www.voxpot.cz/cistejsi-lodni-palivo-el-nino-erupce-i-ceska-anomalie-to-vse-ovlivnilo-necekany-rust-teplot/",
      "title": "Čistější lodní palivo, El Niño, erupce i česká anomálie. To vše ovlivnilo nečekaný růst teplot - VOXPOT",
      "description": "Rekordy na Celsiově stupnici létem neskončily – nejteplejší v historii lidstva bylo i září a začátek října. Na tento trend bychom si přitom měli zvykat, a být zároveň rádi, že žijeme v Česku. Proč to tak je a další souvislosti se změnami klimatu Voxpotu osvětlil klimatolog Jan Řehoř.",
      "language": "cs",
      "type": "link",
      "provider_name": "VOXPOT",
      "width": 2000,
      "height": 1334,
      "image": "https://mastodonczech.cz/system/cache/preview_cards/images/002/360/013/original/147bcd4d348c754d.jpg",
      "blurhash": "UNDw8h-:00Iox]%gozRj9GRj?b%MIVRkoet6",
      "published_at": "2023-10-24T04:01:31+00:00"
    }
  },
  {
    "id": 111292660649004633,
    "created_at": "2023-10-24T23:47:13.050000+00:00",
    "sensitive": false,
    "visibility": "public",
    "language": "cs",
    "uri": "https://mastodonczech.cz/users/honzajavorek/statuses/111292660649004633",
    "url": "https://mastodonczech.cz/@honzajavorek/111292660649004633",
    "favourites_count": 2,
    "favourited": false,
    "reblogged": false,
    "muted": false,
    "bookmarked": false,
    "pinned": false,
    "content": "<p>„It is easy to forget how to talk to a person, because you’re not talking to a person: you’re Replying. Everyone involved is either an abstraction, an ideal, entertainment, or part of an annoying crowdsourced search engine.“ <a href=\"https://dirt.fyi/article/2023/10/what-was-replying\" target=\"_blank\" rel=\"nofollow noopener noreferrer\" translate=\"no\"><span class=\"invisible\">https://</span><span class=\"ellipsis\">dirt.fyi/article/2023/10/what-</span><span class=\"invisible\">was-replying</span></a> <a href=\"https://mastodonczech.cz/tags/links\" class=\"mention hashtag\" rel=\"tag\">#<span>links</span></a></p>",
    "tags": [
      {
        "name": "links",
        "url": "https://mastodonczech.cz/tags/links"
      }
    ],
    "card": {
      "url": "https://dirt.fyi/article/2023/10/what-was-replying",
      "title": "What was 'replying'? ",
      "description": "Shouting into the void that answers back.",
      "language": "en",
      "type": "link",
      "provider_name": "The Dirtyverse",
      "width": 1200,
      "height": 1200,
      "image": "https://mastodonczech.cz/system/cache/preview_cards/images/002/370/692/original/b0afed6b258001ce.jpeg",
      "blurhash": "UZG@fBNGe-oe%2I;IpRk0zs:xas.I;o0xas:",
      "published_at": "2023-10-09T00:00:00+00:00"
    }
  },
  {
    "id": 111291649695013566,
    "created_at": "2023-10-24T19:30:07.117000+00:00",
    "sensitive": false,
    "visibility": "public",
    "language": "cs",
    "uri": "https://mastodonczech.cz/users/honzajavorek/statuses/111291649695013566",
    "url": "https://mastodonczech.cz/@honzajavorek/111291649695013566",
    "replies_count": 1,
    "favourites_count": 2,
    "favourited": false,
    "reblogged": false,
    "muted": false,
    "bookmarked": false,
    "pinned": false,
    "content": "<p>„Firemní kulturu nejde vytvořit, ona prostě je.“ „Kultura není to, co si napíšete na nástěnku, ale to, co děláte. Pokud máte neomezenou dovolenou, ale šéfové si vezmou pár dní volna za rok, lidi mají jasno, jestli svým chováním následovat papír, nebo to, co reálně vidí.“ (volná citace) Pěkně to tam řekli, kluci z 37signals! <a href=\"https://overcast.fm/+JpthCWwIM\" target=\"_blank\" rel=\"nofollow noopener noreferrer\" translate=\"no\"><span class=\"invisible\">https://</span><span class=\"\">overcast.fm/+JpthCWwIM</span><span class=\"invisible\"></span></a> <a href=\"https://mastodonczech.cz/tags/links\" class=\"mention hashtag\" rel=\"tag\">#<span>links</span></a></p>",
    "tags": [
      {
        "name": "links",
        "url": "https://mastodonczech.cz/tags/links"
      }
    ],
    "card": {
      "url": "https://overcast.fm/+JpthCWwIM",
      "title": "You Don’t Create a Culture — REWORK",
      "language": "en",
      "type": "video",
      "html": "<iframe src=\"https://overcast.fm/podcasts/episode_card/679180636700803?t=0\" width=\"290\" height=\"58\" allowfullscreen=\"allowfullscreen\" scrolling=\"no\" frameborder=\"0\" sandbox=\"allow-scripts allow-same-origin allow-popups allow-popups-to-escape-sandbox allow-forms\"></iframe>",
      "width": 290,
      "height": 58,
      "image": "https://mastodonczech.cz/system/cache/preview_cards/images/002/368/663/original/2de33ce905f90e5d.png",
      "embed_url": "https://www.buzzsprout.com/2260539/13768332-you-don-t-create-a-culture.mp3#t=0",
      "blurhash": "UASiaA9Z%#%2n4R*NaV@.Se.a0tR.m%2m,Sg"
    }
  },
  {
    "id": 111277720283090292,
    "created_at": "2023-10-22T08:27:41.159000+00:00",
    "sensitive": false,
    "visibility": "public",
    "language": "cs",
    "uri": "https://mastodonczech.cz/users/honzajavorek/statuses/111277720283090292",
    "url": "https://mastodonczech.cz/@honzajavorek/111277720283090292",
    "replies_count": 1,
    "reblogs_count": 5,
    "favourites_count": 13,
    "favourited": false,
    "reblogged": false,
    "muted": false,
    "bookmarked": false,
    "pinned": false,
    "content": "<p>Skvělý text od Pavlíny Louženské o tom, jak jsme přestali stíhat čas. „Ve chvíli, kdy jsme ztratili dlouhodobý výhled, tak se vracíme ve vnímání času zpátky do mysli šestnáctiletých. Všechno je zásadní. Všechno musíme stihnout než. Všechno měříme v dnech a týdnech, ne v letech.“ „Chci mít chvíli pro sebe. Chci zpomalit. Chci zastavit čas, říkají mi na každém callu a přichází s dalším plánem, jak se optimalizovat. Včetně toho, že si dají do kalendáře cally se mnou.“ <a href=\"https://www.pavlinaspeaks.com/blog/bezcasi\" target=\"_blank\" rel=\"nofollow noopener noreferrer\" translate=\"no\"><span class=\"invisible\">https://www.</span><span class=\"\">pavlinaspeaks.com/blog/bezcasi</span><span class=\"invisible\"></span></a> <a href=\"https://mastodonczech.cz/tags/links\" class=\"mention hashtag\" rel=\"tag\">#<span>links</span></a></p>",
    "tags": [
      {
        "name": "links",
        "url": "https://mastodonczech.cz/tags/links"
      }
    ],
    "card": {
      "url": "https://www.pavlinaspeaks.com/blog/bezcasi",
      "title": "Bezčasí — PAVLINA_SPEAKS",
      "description": "Za posledních padesát let akcelerovaly technologie stejnou rychlostí jako za dvě stě let před tím. Pocit, že je všechno rychlejší není pocit. Je to fakt. Přestali jsme stíhat čas.",
      "language": "en",
      "type": "link",
      "provider_name": "PAVLINA_SPEAKS",
      "width": 1500,
      "height": 454,
      "image": "https://mastodonczech.cz/system/cache/preview_cards/images/002/341/001/original/9915e3e352ef94e3.png",
      "blurhash": "UWBW.1V@RkWB8^j[WCWBRiozs:oftRa#kCj["
    }
  },
  {
    "id": 111272783412635484,
    "created_at": "2023-10-21T11:32:10.494000+00:00",
    "sensitive": false,
    "visibility": "public",
    "language": "cs",
    "uri": "https://mastodonczech.cz/users/honzajavorek/statuses/111272783412635484",
    "url": "https://mastodonczech.cz/@honzajavorek/111272783412635484",
    "favourites_count": 1,
    "favourited": false,
    "reblogged": false,
    "muted": false,
    "bookmarked": false,
    "pinned": false,
    "content": "<p>Stárneme a už nejsme cool. Mileniálové ale prý stárnou úplně jinak, než předchozí generace. Pomalu. A s nadcházející mladou generací sdílí spoustu hodnot. <a href=\"https://seznam-zpravy.u.mailkit.eu/mc/VUCQVPEU/ATOZNRVLHALPTQWAJS/CLMLMPUELCI\" target=\"_blank\" rel=\"nofollow noopener noreferrer\" translate=\"no\"><span class=\"invisible\">https://</span><span class=\"ellipsis\">seznam-zpravy.u.mailkit.eu/mc/</span><span class=\"invisible\">VUCQVPEU/ATOZNRVLHALPTQWAJS/CLMLMPUELCI</span></a> <a href=\"https://mastodonczech.cz/tags/links\" class=\"mention hashtag\" rel=\"tag\">#<span>links</span></a></p>",
    "tags": [
      {
        "name": "links",
        "url": "https://mastodonczech.cz/tags/links"
      }
    ],
    "card": {
      "url": "https://seznam-zpravy.u.mailkit.eu/mc/VUCQVPEU/ATOZNRVLHALPTQWAJS/CLMLMPUELCI",
      "title": "Pod čarou: Každá generace zestárne stejně. Mileniálové jsou ale výjimka.",
      "type": "link"
    }
  },
  {
    "id": 111272296766548555,
    "created_at": "2023-10-21T09:28:25.079000+00:00",
    "sensitive": false,
    "visibility": "public",
    "language": "cs",
    "uri": "https://mastodonczech.cz/users/honzajavorek/statuses/111272296766548555",
    "url": "https://mastodonczech.cz/@honzajavorek/111272296766548555",
    "replies_count": 1,
    "favourites_count": 2,
    "favourited": false,
    "reblogged": false,
    "muted": false,
    "bookmarked": false,
    "pinned": false,
    "content": "<p>Tohle si sem teď uložím a až bude dcera větší, odkaz vyhrabu. Třeba ji to bude bavit tak jako kdysi mně. (A třeba ne a naučí mě Minecraft.) <a href=\"http://www.papirovemodelarstvi.cz/phpBB3/\" target=\"_blank\" rel=\"nofollow noopener noreferrer\" translate=\"no\"><span class=\"invisible\">http://www.</span><span class=\"\">papirovemodelarstvi.cz/phpBB3/</span><span class=\"invisible\"></span></a> <a href=\"https://mastodonczech.cz/tags/links\" class=\"mention hashtag\" rel=\"tag\">#<span>links</span></a></p>",
    "tags": [
      {
        "name": "links",
        "url": "https://mastodonczech.cz/tags/links"
      }
    ],
    "card": {
      "url": "http://www.papirovemodelarstvi.cz/phpBB3/",
      "title": "Papírové modelářství CZ • Obsah",
      "language": "cs",
      "type": "link"
    }
  },
  {
    "id": 111264006260630561,
    "created_at": "2023-10-19T22:20:01.800000+00:00",
    "sensitive": false,
    "visibility": "public",
    "language": "cs",
    "uri": "https://mastodonczech.cz/users/honzajavorek/statuses/111264006260630561",
    "url": "https://mastodonczech.cz/@honzajavorek/111264006260630561",
    "replies_count": 1,
    "favourites_count": 2,
    "edited_at": "2023-10-21T09:04:05.784000+00:00",
    "favourited": false,
    "reblogged": false,
    "muted": false,
    "bookmarked": false,
    "pinned": false,
    "content": "<p>Já vím, že <a href=\"https://mastodonczech.cz/tags/Firefox\" class=\"mention hashtag\" rel=\"tag\">#<span>Firefox</span></a> má kontejnery a tak, ale tyjo, já chci tohle přepínátko, které zrovna přidali do <a href=\"https://mastodonczech.cz/tags/Safari\" class=\"mention hashtag\" rel=\"tag\">#<span>Safari</span></a>. Jak to mám udělat? <a href=\"https://support.apple.com/en-us/HT212544\" target=\"_blank\" rel=\"nofollow noopener noreferrer\" translate=\"no\"><span class=\"invisible\">https://</span><span class=\"ellipsis\">support.apple.com/en-us/HT2125</span><span class=\"invisible\">44</span></a> <a href=\"https://mastodonczech.cz/tags/links\" class=\"mention hashtag\" rel=\"tag\">#<span>links</span></a></p>",
    "media_attachments": [
      {
        "id": 111264003660054047,
        "type": "image",
        "url": "https://mastodonczech.cz/system/media_attachments/files/111/264/003/660/054/047/original/ebf48cbfa1e7d066.png",
        "preview_url": "https://mastodonczech.cz/system/media_attachments/files/111/264/003/660/054/047/small/ebf48cbfa1e7d066.png",
        "meta": {
          "original": {
            "width": 950,
            "height": 700,
            "size": "950x700",
            "aspect": 1.3571428571428572
          },
          "small": {
            "width": 559,
            "height": 412,
            "size": "559x412",
            "aspect": 1.3567961165048543
          }
        },
        "blurhash": "UlMH$Rs+NM-g~MR-fQR.xaoc$_NL$_a#WFfQ"
      }
    ],
    "tags": [
      {
        "name": "firefox",
        "url": "https://mastodonczech.cz/tags/firefox"
      },
      {
        "name": "links",
        "url": "https://mastodonczech.cz/tags/links"
      },
      {
        "name": "safari",
        "url": "https://mastodonczech.cz/tags/safari"
      }
    ],
    "card": {
      "url": "https://support.apple.com/en-us/HT212544",
      "title": "Use profiles in Safari on Mac",
      "description": "Starting with Safari 17, you can use profiles to keep your browsing separate for topics like work, personal, or school. Each profile has separate history, cookies, website data, extensions, Tab Groups, and favorites.\n\n",
      "language": "en",
      "type": "link",
      "provider_name": "Apple Support"
    }
  },
  {
    "id": 111263822139805969,
    "created_at": "2023-10-19T21:33:12.321000+00:00",
    "sensitive": false,
    "visibility": "public",
    "language": "cs",
    "uri": "https://mastodonczech.cz/users/honzajavorek/statuses/111263822139805969",
    "url": "https://mastodonczech.cz/@honzajavorek/111263822139805969",
    "reblogs_count": 2,
    "favourites_count": 2,
    "favourited": false,
    "reblogged": false,
    "muted": false,
    "bookmarked": false,
    "pinned": false,
    "content": "<p>Ano prosím. Už to mělo být dávno. <a href=\"https://zdopravy.cz/misto-zabradli-sloupky-praha-chce-zacit-odstranovat-cerveno-bile-ohradky-v-ulicich-181171/\" target=\"_blank\" rel=\"nofollow noopener noreferrer\" translate=\"no\"><span class=\"invisible\">https://</span><span class=\"ellipsis\">zdopravy.cz/misto-zabradli-slo</span><span class=\"invisible\">upky-praha-chce-zacit-odstranovat-cerveno-bile-ohradky-v-ulicich-181171/</span></a> <a href=\"https://mastodonczech.cz/tags/links\" class=\"mention hashtag\" rel=\"tag\">#<span>links</span></a></p>",
    "tags": [
      {
        "name": "links",
        "url": "https://mastodonczech.cz/tags/links"
      }
    ],
    "card": {
      "url": "https://zdopravy.cz/misto-zabradli-sloupky-praha-chce-zacit-odstranovat-cerveno-bile-ohradky-v-ulicich-181171/",
      "title": "Místo zábradlí sloupky. Praha chce začít odstraňovat červeno-bílé \"ohrádky\" v ulicích - Zdopravy.cz",
      "description": "Barevná trubková zábradlí podle náměstka Zdeňka Hřiba kazí dojem z města a jsou často nadbytečná.",
      "language": "cs",
      "type": "link",
      "provider_name": "Zdopravy.cz",
      "width": 1553,
      "height": 726,
      "image": "https://mastodonczech.cz/system/cache/preview_cards/images/002/316/921/original/1791110e3ce1a74b.jpg",
      "blurhash": "UYF6IPRPjZxu~qIps;t7_2bcj[ay.8afayay",
      "published_at": "2023-10-19T15:15:56+00:00"
    }
  },
  {
    "id": 111245493506984827,
    "created_at": "2023-10-16T15:51:59.578000+00:00",
    "sensitive": false,
    "visibility": "public",
    "language": "cs",
    "uri": "https://mastodonczech.cz/users/honzajavorek/statuses/111245493506984827",
    "url": "https://mastodonczech.cz/@honzajavorek/111245493506984827",
    "favourited": false,
    "reblogged": false,
    "muted": false,
    "bookmarked": false,
    "pinned": false,
    "content": "<p>Zajímavý článek o vztahu firem a frontendových frameworků. Licence, partnerství, sponzorství, ukončená partnerství, akvizice a co z toho všechno plyne… <a href=\"https://redmonk.com/kholterhoff/2023/10/03/indie-oss-jsframeworks/\" target=\"_blank\" rel=\"nofollow noopener noreferrer\" translate=\"no\"><span class=\"invisible\">https://</span><span class=\"ellipsis\">redmonk.com/kholterhoff/2023/1</span><span class=\"invisible\">0/03/indie-oss-jsframeworks/</span></a> <a href=\"https://mastodonczech.cz/tags/links\" class=\"mention hashtag\" rel=\"tag\">#<span>links</span></a></p>",
    "tags": [
      {
        "name": "links",
        "url": "https://mastodonczech.cz/tags/links"
      }
    ],
    "card": {
      "url": "https://redmonk.com/kholterhoff/2023/10/03/indie-oss-jsframeworks/",
      "title": "The Indie, Open Source JavaScript Frameworks Developers Love, and the Risks of Commercial Relationships",
      "description": "The frontend community is abuzz about the recently announced partnership between Vercel and Astro. This is not the first highly publicized relationship between an infrastructure platform targeted to frontend developers, and an indie, open source (OSS) Javascript (JS) framework. In addition to Vercel and Astro, Shopify announced its partnership with Remix in 2022, and this",
      "language": "en",
      "type": "link",
      "provider_name": "console.log()"
    }
  },
  {
    "id": 111245489234054196,
    "created_at": "2023-10-16T15:50:54.379000+00:00",
    "sensitive": false,
    "visibility": "public",
    "language": "cs",
    "uri": "https://mastodonczech.cz/users/honzajavorek/statuses/111245489234054196",
    "url": "https://mastodonczech.cz/@honzajavorek/111245489234054196",
    "replies_count": 1,
    "favourites_count": 1,
    "favourited": false,
    "reblogged": false,
    "muted": false,
    "bookmarked": false,
    "pinned": false,
    "content": "<p>Znamená „open source“ vlastně ještě něco? Záleží vůbec ještě někomu na licencích? „The goal of open source, of cloud, of open APIs, of great documentation, etc., is to enable developers to build with less friction and more opportunity. Is Llama 2 open enough for 99.999% of the developer population to use it with unfettered access? Yes. Is it “open source”? The question doesn’t really matter.“ <a href=\"https://www.infoworld.com/article/3703768/the-open-source-licensing-war-is-over.html\" target=\"_blank\" rel=\"nofollow noopener noreferrer\" translate=\"no\"><span class=\"invisible\">https://www.</span><span class=\"ellipsis\">infoworld.com/article/3703768/</span><span class=\"invisible\">the-open-source-licensing-war-is-over.html</span></a> <a href=\"https://mastodonczech.cz/tags/links\" class=\"mention hashtag\" rel=\"tag\">#<span>links</span></a></p>",
    "tags": [
      {
        "name": "links",
        "url": "https://mastodonczech.cz/tags/links"
      }
    ],
    "card": {
      "url": "https://www.infoworld.com/article/3703768/the-open-source-licensing-war-is-over.html",
      "title": "The open source licensing war is over",
      "description": "It’s time for the open source Rambos to stop fighting and agree that developers care more about software’s access and ease of use than the purity of its license.",
      "language": "en",
      "type": "link",
      "provider_name": "InfoWorld",
      "width": 1200,
      "height": 800,
      "image": "https://mastodonczech.cz/system/cache/preview_cards/images/001/511/591/original/ebdd27cae4ce6f11.jpg",
      "blurhash": "UjFZw1t64=WCt5oeR+ay0OfP--a#RlWBt5of"
    }
  },
  {
    "id": 111241088647000479,
    "created_at": "2023-10-15T21:11:46.749000+00:00",
    "sensitive": false,
    "visibility": "public",
    "language": "cs",
    "uri": "https://mastodonczech.cz/users/honzajavorek/statuses/111241088647000479",
    "url": "https://mastodonczech.cz/@honzajavorek/111241088647000479",
    "reblogs_count": 1,
    "favourites_count": 3,
    "favourited": false,
    "reblogged": false,
    "muted": false,
    "bookmarked": false,
    "pinned": false,
    "content": "<p>Pomohlo mi to zorientovat se v aktuálním dění v Palestině a Izraeli. Něco jsem věděl, něco ne. <a href=\"https://www.nihilistanabalkonu.cz/l/co-se-to-deje-v-izraeli/\" target=\"_blank\" rel=\"nofollow noopener noreferrer\" translate=\"no\"><span class=\"invisible\">https://www.</span><span class=\"ellipsis\">nihilistanabalkonu.cz/l/co-se-</span><span class=\"invisible\">to-deje-v-izraeli/</span></a> <a href=\"https://mastodonczech.cz/tags/links\" class=\"mention hashtag\" rel=\"tag\">#<span>links</span></a></p>",
    "tags": [
      {
        "name": "links",
        "url": "https://mastodonczech.cz/tags/links"
      }
    ],
    "card": {
      "url": "https://www.nihilistanabalkonu.cz/l/co-se-to-deje-v-izraeli/",
      "title": "Co se to děje v Izraeli? :: Nihilista",
      "description": "Na počátku 90. let se řada lidí domnívala, že s koncem studené války dojde postupně k úplnému globálnímu vítězství demokracie a ekonomického liberalismu, čímž dějiny v podstatě skončí a ve světě už se vlastně nebude nic moc zásadního dít. Budoucí historici se unudí k smrti a senzacechtiví novináři nebudou mít co žrát. V té době to tak totiž opravdu...",
      "language": "cs",
      "type": "link",
      "provider_name": "Nihilista",
      "width": 700,
      "height": 466,
      "image": "https://mastodonczech.cz/system/cache/preview_cards/images/002/265/926/original/d56b5fa326aeb5e5.jpeg",
      "blurhash": "USEooXs+4mS7xBWCXAoID%bco#jDtSf6ROog"
    }
  },
  {
    "id": 111206257682826824,
    "created_at": "2023-10-09T17:33:48.418000+00:00",
    "sensitive": false,
    "visibility": "public",
    "language": "cs",
    "uri": "https://mastodonczech.cz/users/honzajavorek/statuses/111206257682826824",
    "url": "https://mastodonczech.cz/@honzajavorek/111206257682826824",
    "favourites_count": 2,
    "favourited": false,
    "reblogged": false,
    "muted": false,
    "bookmarked": false,
    "pinned": false,
    "content": "<p>Ať vás F1 zajímá nebo ne, tohle je prostě neskutečný. McLaren má nový světový rekord v nejrychlejším pitstopu: 1,80 sekundy. <a href=\"https://nitter.cz/StevoEisele/status/1711157019942535282#m\" target=\"_blank\" rel=\"nofollow noopener noreferrer\" translate=\"no\"><span class=\"invisible\">https://</span><span class=\"ellipsis\">nitter.cz/StevoEisele/status/1</span><span class=\"invisible\">711157019942535282#m</span></a> <a href=\"https://mastodonczech.cz/tags/links\" class=\"mention hashtag\" rel=\"tag\">#<span>links</span></a></p>",
    "tags": [
      {
        "name": "links",
        "url": "https://mastodonczech.cz/tags/links"
      }
    ]
  },
  {
    "id": 111206225307483271,
    "created_at": "2023-10-09T17:25:34.404000+00:00",
    "sensitive": false,
    "visibility": "public",
    "language": "cs",
    "uri": "https://mastodonczech.cz/users/honzajavorek/statuses/111206225307483271",
    "url": "https://mastodonczech.cz/@honzajavorek/111206225307483271",
    "replies_count": 1,
    "favourites_count": 1,
    "favourited": false,
    "reblogged": false,
    "muted": false,
    "bookmarked": false,
    "pinned": false,
    "content": "<p>„The only status symbol worth looking out for is an invisible one: The degree of control people have over their own time. It comes with seniority, financial independence and good life choices.“ Jako jo, souhlas, a osobně to mám teď dost vyladěné, ale očekávám, že např. školka mi do toho asi hodí dost vidle. Good life choices? 😅 <a href=\"https://nitter.cz/DKellyArchitect/status/1711045026262683892#m\" target=\"_blank\" rel=\"nofollow noopener noreferrer\" translate=\"no\"><span class=\"invisible\">https://</span><span class=\"ellipsis\">nitter.cz/DKellyArchitect/stat</span><span class=\"invisible\">us/1711045026262683892#m</span></a> <a href=\"https://mastodonczech.cz/tags/links\" class=\"mention hashtag\" rel=\"tag\">#<span>links</span></a></p>",
    "tags": [
      {
        "name": "links",
        "url": "https://mastodonczech.cz/tags/links"
      }
    ]
  },
  {
    "id": 111204032467792112,
    "created_at": "2023-10-09T08:07:54.327000+00:00",
    "sensitive": false,
    "visibility": "public",
    "language": "cs",
    "uri": "https://mastodonczech.cz/users/honzajavorek/statuses/111204032467792112",
    "url": "https://mastodonczech.cz/@honzajavorek/111204032467792112",
    "reblogs_count": 2,
    "favourites_count": 3,
    "favourited": false,
    "reblogged": false,
    "muted": false,
    "bookmarked": false,
    "pinned": false,
    "content": "<p>Proč udržovat CHANGELOG soubor a jak. <a href=\"https://keepachangelog.com/\" target=\"_blank\" rel=\"nofollow noopener noreferrer\" translate=\"no\"><span class=\"invisible\">https://</span><span class=\"\">keepachangelog.com/</span><span class=\"invisible\"></span></a> <a href=\"https://mastodonczech.cz/tags/links\" class=\"mention hashtag\" rel=\"tag\">#<span>links</span></a></p>",
    "tags": [
      {
        "name": "links",
        "url": "https://mastodonczech.cz/tags/links"
      }
    ]
  },
  {
    "id": 111199463002763650,
    "created_at": "2023-10-08T12:45:49.826000+00:00",
    "sensitive": false,
    "visibility": "public",
    "language": "cs",
    "uri": "https://mastodonczech.cz/users/honzajavorek/statuses/111199463002763650",
    "url": "https://mastodonczech.cz/@honzajavorek/111199463002763650",
    "reblogs_count": 1,
    "favourites_count": 3,
    "favourited": false,
    "reblogged": false,
    "muted": false,
    "bookmarked": false,
    "pinned": false,
    "content": "<p>„Záplava informací a sporů z nás dělá hypergramotné čtenáře doby. Učíme se způsob čtení, jehož cílem je co nejrychleji ideologicky rozřazovat. Šetří to čas i nervy: nebudu se bavit s člověkem, co používá TOHLE slovo.“ „Sledujeme performativní polarizaci. V ní vlivní hráči možná nenabízejí lákavý program, druhou stranu však vykreslují tak děsivě, že se jim skrze konflikt podaří sjednotit vlastní podporovatele.” <a href=\"https://www.mediar.cz/palme-do-vlastnich-rad/\" target=\"_blank\" rel=\"nofollow noopener noreferrer\" translate=\"no\"><span class=\"invisible\">https://www.</span><span class=\"ellipsis\">mediar.cz/palme-do-vlastnich-r</span><span class=\"invisible\">ad/</span></a> <a href=\"https://mastodonczech.cz/tags/links\" class=\"mention hashtag\" rel=\"tag\">#<span>links</span></a></p>",
    "tags": [
      {
        "name": "links",
        "url": "https://mastodonczech.cz/tags/links"
      }
    ],
    "card": {
      "url": "https://www.mediar.cz/palme-do-vlastnich-rad/",
      "title": "Palme do vlastních řad",
      "description": "Kritika vlastního tábora vysvobozuje ze zákopů kulturních válek.",
      "language": "cs",
      "type": "link",
      "provider_name": "Médiář",
      "width": 1200,
      "height": 800,
      "image": "https://mastodonczech.cz/system/cache/preview_cards/images/002/187/010/original/a78bfdff6326d0fe.jpg",
      "image_description": "Zdroj: Midjourney",
      "blurhash": "UjL3GNo0IBR+}roLwvR+v#s:-oR+wJWWoebH",
      "published_at": "2023-10-07T22:00:00+00:00"
    }
  },
  {
    "id": 111199460895235536,
    "created_at": "2023-10-08T12:45:17.685000+00:00",
    "sensitive": false,
    "visibility": "public",
    "language": "cs",
    "uri": "https://mastodonczech.cz/users/honzajavorek/statuses/111199460895235536",
    "url": "https://mastodonczech.cz/@honzajavorek/111199460895235536",
    "favourites_count": 6,
    "favourited": false,
    "reblogged": false,
    "muted": false,
    "bookmarked": false,
    "pinned": false,
    "content": "<p>Lol, Mozilla se podívala na to, jak výrobci aut zacházejí s osobními daty a je to naprostá katastrofa. Úplně všechny značky to mají úplně na párku a dají se seřadit jen od velmi špatných po nejhorší. <a href=\"https://foundation.mozilla.org/en/privacynotincluded/articles/its-official-cars-are-the-worst-product-category-we-have-ever-reviewed-for-privacy/\" target=\"_blank\" rel=\"nofollow noopener noreferrer\" translate=\"no\"><span class=\"invisible\">https://</span><span class=\"ellipsis\">foundation.mozilla.org/en/priv</span><span class=\"invisible\">acynotincluded/articles/its-official-cars-are-the-worst-product-category-we-have-ever-reviewed-for-privacy/</span></a> <a href=\"https://mastodonczech.cz/tags/links\" class=\"mention hashtag\" rel=\"tag\">#<span>links</span></a></p>",
    "tags": [
      {
        "name": "links",
        "url": "https://mastodonczech.cz/tags/links"
      }
    ],
    "card": {
      "url": "https://foundation.mozilla.org/en/privacynotincluded/articles/its-official-cars-are-the-worst-product-category-we-have-ever-reviewed-for-privacy/",
      "title": "*Privacy Not Included: A Buyer’s Guide for Connected Products",
      "description": "All 25 car brands we researched earned our *Privacy Not Included warning label – making cars the worst category of products that we have ever reviewed",
      "language": "en",
      "type": "link",
      "provider_name": "Mozilla Foundation",
      "width": 2500,
      "height": 1309,
      "image": "https://mastodonczech.cz/system/cache/preview_cards/images/001/842/386/original/0208da1c76f8a7fb.png",
      "blurhash": "UUOM,H?QwERj~M9jsjxtROxtt7RjIwxSbcj^"
    }
  },
  {
    "id": 111195350445171506,
    "created_at": "2023-10-07T19:19:57.191000+00:00",
    "sensitive": false,
    "visibility": "public",
    "language": "cs",
    "uri": "https://mastodonczech.cz/users/honzajavorek/statuses/111195350445171506",
    "url": "https://mastodonczech.cz/@honzajavorek/111195350445171506",
    "replies_count": 1,
    "reblogs_count": 1,
    "favourites_count": 2,
    "favourited": false,
    "reblogged": false,
    "muted": false,
    "bookmarked": false,
    "pinned": false,
    "content": "<p>Frontendu nerozumím natolik, abych tohle nějak komentoval, ale bylo to rozhodně zajímavé čtení. A objevil jsem díky němu věci jako petite-vue nebo alpine, které bych teoreticky někdy mohl využít. <a href=\"https://joshcollinsworth.com/blog/antiquated-react\" target=\"_blank\" rel=\"nofollow noopener noreferrer\" translate=\"no\"><span class=\"invisible\">https://</span><span class=\"ellipsis\">joshcollinsworth.com/blog/anti</span><span class=\"invisible\">quated-react</span></a> <a href=\"https://mastodonczech.cz/tags/links\" class=\"mention hashtag\" rel=\"tag\">#<span>links</span></a></p>",
    "tags": [
      {
        "name": "links",
        "url": "https://mastodonczech.cz/tags/links"
      }
    ],
    "card": {
      "url": "https://joshcollinsworth.com/blog/antiquated-react/",
      "title": "Things you forgot (or never knew) because of React",
      "description": "If you don't often look beyond established comfortable defaults, you might be surprised to learn just how far the world of frontend has moved away from React, and how big that gap continues to grow.",
      "language": "en",
      "type": "link",
      "provider_name": "Josh Collinsworth",
      "width": 1920,
      "height": 1080,
      "image": "https://mastodonczech.cz/system/cache/preview_cards/images/001/533/785/original/91c0f8dcd9811373.png",
      "blurhash": "UESs88s9ozozofj[fQay~WS4WAWAayayj[kC"
    }
  },
  {
    "id": 111189704253488785,
    "created_at": "2023-10-06T19:24:03.127000+00:00",
    "sensitive": false,
    "visibility": "public",
    "language": "cs",
    "uri": "https://mastodonczech.cz/users/honzajavorek/statuses/111189704253488785",
    "url": "https://mastodonczech.cz/@honzajavorek/111189704253488785",
    "favourited": false,
    "reblogged": false,
    "muted": false,
    "bookmarked": false,
    "pinned": false,
    "content": "<p>Jsou Python konference v Africe bezpečné? Žádné konference nejsou. Ale u těch na Západě nás nenapadne se na to ptát. „It would be quite a surprise if the organisers of a Python event in the West were to issue safety guidance to black or African attendees. But one doesn’t need to look far to find examples of black community members who have encountered racism while visiting Python events - in countries that no-one would raise concerns about supporting.“ <a href=\"https://vurt.eu/articles/on-safety/\" target=\"_blank\" rel=\"nofollow noopener noreferrer\" translate=\"no\"><span class=\"invisible\">https://</span><span class=\"\">vurt.eu/articles/on-safety/</span><span class=\"invisible\"></span></a> <a href=\"https://mastodonczech.cz/tags/links\" class=\"mention hashtag\" rel=\"tag\">#<span>links</span></a></p>",
    "tags": [
      {
        "name": "links",
        "url": "https://mastodonczech.cz/tags/links"
      }
    ],
    "card": {
      "url": "https://vurt.eu/articles/on-safety/",
      "title": "A perspective on attendee safety at Python community events - Daniele Procida",
      "language": "en",
      "type": "link"
    }
  },
  {
    "id": 111189620617145923,
    "created_at": "2023-10-06T19:02:46.938000+00:00",
    "sensitive": false,
    "visibility": "public",
    "language": "cs",
    "uri": "https://mastodonczech.cz/users/honzajavorek/statuses/111189620617145923",
    "url": "https://mastodonczech.cz/@honzajavorek/111189620617145923",
    "replies_count": 2,
    "favourites_count": 4,
    "favourited": false,
    "reblogged": false,
    "muted": false,
    "bookmarked": false,
    "pinned": false,
    "content": "<p>Už se těším, až to uvidím! V Pardubicích otevřeli Gočárovy mlýny. <a href=\"https://magazin.aktualne.cz/bydleni/architektura/meli-si-koupit-hezky-byt-manzele-otevreli-gocarovy-mlyny-opr/r~1ef2271861ef11eea9eeac1f6b220ee8/r~3cac7782629811ee8d680cc47ab5f122/\" target=\"_blank\" rel=\"nofollow noopener noreferrer\" translate=\"no\"><span class=\"invisible\">https://</span><span class=\"ellipsis\">magazin.aktualne.cz/bydleni/ar</span><span class=\"invisible\">chitektura/meli-si-koupit-hezky-byt-manzele-otevreli-gocarovy-mlyny-opr/r~1ef2271861ef11eea9eeac1f6b220ee8/r~3cac7782629811ee8d680cc47ab5f122/</span></a> <a href=\"https://mastodonczech.cz/tags/links\" class=\"mention hashtag\" rel=\"tag\">#<span>links</span></a></p>",
    "tags": [
      {
        "name": "links",
        "url": "https://mastodonczech.cz/tags/links"
      }
    ],
    "card": {
      "url": "https://magazin.aktualne.cz/bydleni/architektura/meli-si-koupit-hezky-byt-manzele-otevreli-gocarovy-mlyny-opr/r~1ef2271861ef11eea9eeac1f6b220ee8/r~3cac7782629811ee8d680cc47ab5f122/",
      "title": "\"Krásné, ale jde z toho hrůza.\" Manželé otevřeli Gočárovy mlýny s obnovou za miliardu",
      "description": "Představení Automatických mlýnů v Pardubicích přilákalo podobné množství lidí jako otevřený Pražský hrad. Co všechno v areálu najdete?",
      "language": "cs",
      "type": "link",
      "author_name": "Magdaléna Medková",
      "provider_name": "Aktuálně.cz",
      "width": 1312,
      "height": 1952,
      "blurhash": "UkG9EnI9t7jFcbxBRjjZX:V@slbHNytRWAju",
      "published_at": "2023-10-06T04:00:00+00:00"
    }
  },
  {
    "id": 111188429223223108,
    "created_at": "2023-10-06T13:59:47.709000+00:00",
    "sensitive": false,
    "visibility": "public",
    "language": "cs",
    "uri": "https://mastodonczech.cz/users/honzajavorek/statuses/111188429223223108",
    "url": "https://mastodonczech.cz/@honzajavorek/111188429223223108",
    "favourited": false,
    "reblogged": false,
    "muted": false,
    "bookmarked": false,
    "pinned": false,
    "content": "<p>Věděli jste, že skupinu na Facebooku nelze žádným normálním způsobem úplně zrušit a smazat? <a href=\"https://www.facebook.com/help/174988392554409/\" target=\"_blank\" rel=\"nofollow noopener noreferrer\" translate=\"no\"><span class=\"invisible\">https://www.</span><span class=\"ellipsis\">facebook.com/help/174988392554</span><span class=\"invisible\">409/</span></a> <a href=\"https://mastodonczech.cz/tags/links\" class=\"mention hashtag\" rel=\"tag\">#<span>links</span></a></p>",
    "tags": [
      {
        "name": "links",
        "url": "https://mastodonczech.cz/tags/links"
      }
    ]
  },
  {
    "id": 111187826135342980,
    "created_at": "2023-10-06T11:26:25.323000+00:00",
    "sensitive": false,
    "visibility": "public",
    "language": "cs",
    "uri": "https://mastodonczech.cz/users/honzajavorek/statuses/111187826135342980",
    "url": "https://mastodonczech.cz/@honzajavorek/111187826135342980",
    "replies_count": 3,
    "favourites_count": 2,
    "favourited": false,
    "reblogged": false,
    "muted": false,
    "bookmarked": false,
    "pinned": false,
    "content": "<p>Bun. TypeScript. Yarn. CoffeeScript. Stále stejná pohádka? Hype vynese novou technologii do oblak, aby pak všechny její funkce implementoval původní ekosystém a udělal z ní pouze kapitolu dějin. Autor naznačuje, že tyhle věci způsobují jen zmatek a ukrajují zdroje původnímu ekosystému. Otázka je, zda by se bez nich původní ekosystém inovoval, nebo zda by se ty vyhypované funkce nikdy nestaly prioritou vývoje 🤔 <a href=\"https://dev.to/thejaredwilcurt/bun-hype-how-we-learned-nothing-from-yarn-2n3j\" target=\"_blank\" rel=\"nofollow noopener noreferrer\" translate=\"no\"><span class=\"invisible\">https://</span><span class=\"ellipsis\">dev.to/thejaredwilcurt/bun-hyp</span><span class=\"invisible\">e-how-we-learned-nothing-from-yarn-2n3j</span></a> <a href=\"https://mastodonczech.cz/tags/links\" class=\"mention hashtag\" rel=\"tag\">#<span>links</span></a></p>",
    "tags": [
      {
        "name": "links",
        "url": "https://mastodonczech.cz/tags/links"
      }
    ],
    "card": {
      "url": "https://dev.to/thejaredwilcurt/bun-hype-how-we-learned-nothing-from-yarn-2n3j",
      "title": "Bun hype. How we learned nothing from Yarn",
      "description": "Here we go again, making the same mistake. I'm constantly reminded that every 5 years the amount of...",
      "language": "en",
      "type": "link",
      "provider_name": "DEV Community",
      "width": 1000,
      "height": 500,
      "blurhash": "UFRysgM_t7xu00ayxuRjIUxuIUWBD%ofRjof"
    }
  },
  {
    "id": 111184531932166630,
    "created_at": "2023-10-05T21:28:39.822000+00:00",
    "sensitive": false,
    "visibility": "public",
    "language": "cs",
    "uri": "https://mastodonczech.cz/users/honzajavorek/statuses/111184531932166630",
    "url": "https://mastodonczech.cz/@honzajavorek/111184531932166630",
    "reblogs_count": 1,
    "favourites_count": 1,
    "favourited": false,
    "reblogged": false,
    "muted": false,
    "bookmarked": false,
    "pinned": false,
    "content": "<p>„We can share a screen when we get stuck, and we can share it not with the closest person, but with the best person.“ „…connections at the office… didn’t work for everyone in the same way. They often reinforced status roles and privilege. They were unevenly distributed and didn’t usually appear when we needed them. All of which added up to a new layer of stress for many people.“ <a href=\"https://seths.blog/2021/09/intentional-connection-in-the-digital-office/\" target=\"_blank\" rel=\"nofollow noopener noreferrer\" translate=\"no\"><span class=\"invisible\">https://</span><span class=\"ellipsis\">seths.blog/2021/09/intentional</span><span class=\"invisible\">-connection-in-the-digital-office/</span></a> <a href=\"https://mastodonczech.cz/tags/links\" class=\"mention hashtag\" rel=\"tag\">#<span>links</span></a></p>",
    "tags": [
      {
        "name": "links",
        "url": "https://mastodonczech.cz/tags/links"
      }
    ],
    "card": {
      "url": "https://seths.blog/2021/09/intentional-connection-in-the-digital-office/",
      "title": "Intentional connection in the digital office",
      "description": "The virtual office skeptic says, “we can’t go fully remote, because the serendipity of personal connection is too important.” The theory goes that watercooler conversations and el…",
      "language": "en",
      "type": "link",
      "provider_name": "Seth's Blog",
      "width": 1200,
      "height": 628,
      "blurhash": "UYP}On17I]$wX9kDWXRk}*xBn~S5skWBfQt6",
      "published_at": "2021-09-07T08:04:00+00:00"
    }
  },
  {
    "id": 111184408254679722,
    "created_at": "2023-10-05T20:57:12.599000+00:00",
    "sensitive": false,
    "visibility": "public",
    "language": "cs",
    "uri": "https://mastodonczech.cz/users/honzajavorek/statuses/111184408254679722",
    "url": "https://mastodonczech.cz/@honzajavorek/111184408254679722",
    "favourited": false,
    "reblogged": false,
    "muted": false,
    "bookmarked": false,
    "pinned": false,
    "content": "<p>„4500 lines of organic python… The number of people able to understand its code entanglement was varying between 0 and 1, depending on the quality of my morning Earl Grey.“ <a href=\"https://ploum.net/2023-10-01-future-of-offpunk-packaging-hell.html\" target=\"_blank\" rel=\"nofollow noopener noreferrer\" translate=\"no\"><span class=\"invisible\">https://</span><span class=\"ellipsis\">ploum.net/2023-10-01-future-of</span><span class=\"invisible\">-offpunk-packaging-hell.html</span></a> <a href=\"https://mastodonczech.cz/tags/links\" class=\"mention hashtag\" rel=\"tag\">#<span>links</span></a></p>",
    "tags": [
      {
        "name": "links",
        "url": "https://mastodonczech.cz/tags/links"
      }
    ],
    "card": {
      "url": "https://ploum.net/2023-10-01-future-of-offpunk-packaging-hell.html",
      "title": "The future of Offpunk: UNIX command-line heaven and packaging hell",
      "description": "The future of Offpunk: UNIX command-line heaven and packaging hell écrit par Ploum, Lionel Dricot, ingénieur, écrivain de science-fiction, développeur de logiciels libres.",
      "language": "en",
      "type": "link",
      "width": 400,
      "height": 421,
      "blurhash": "UGB:4}E#0f,@IAE1xa%LO@%1a0EMEL-Ut7Nb"
    }
  },
  {
    "id": 111178800439351458,
    "created_at": "2023-10-04T21:11:04.152000+00:00",
    "sensitive": false,
    "visibility": "public",
    "language": "cs",
    "uri": "https://mastodonczech.cz/users/honzajavorek/statuses/111178800439351458",
    "url": "https://mastodonczech.cz/@honzajavorek/111178800439351458",
    "favourites_count": 2,
    "favourited": false,
    "reblogged": false,
    "muted": false,
    "bookmarked": false,
    "pinned": false,
    "content": "<p>„At the time of the Luddites, many hoped the subpar products would prove unacceptable to consumers or to the government. Instead, social norms adjusted. Both the mass-manufactured products and the regimented jobs that produced them quickly became entrenched.“ <a href=\"https://www.newyorker.com/books/page-turner/rethinking-the-luddites-in-the-age-of-ai\" target=\"_blank\" rel=\"nofollow noopener noreferrer\" translate=\"no\"><span class=\"invisible\">https://www.</span><span class=\"ellipsis\">newyorker.com/books/page-turne</span><span class=\"invisible\">r/rethinking-the-luddites-in-the-age-of-ai</span></a> <a href=\"https://mastodonczech.cz/tags/links\" class=\"mention hashtag\" rel=\"tag\">#<span>links</span></a></p>",
    "tags": [
      {
        "name": "links",
        "url": "https://mastodonczech.cz/tags/links"
      }
    ],
    "card": {
      "url": "https://www.newyorker.com/books/page-turner/rethinking-the-luddites-in-the-age-of-ai",
      "title": "Rethinking the Luddites in the Age of A.I.",
      "description": "Kyle Chayka writes about Brian Merchant’s new book, “Blood in the Machine,” on Luddism’s advocacy for the rights of workers in the face of automation.",
      "language": "en",
      "type": "link",
      "author_name": "Kyle Chayka",
      "provider_name": "The New Yorker",
      "width": 1280,
      "height": 720,
      "blurhash": "UBAv%v~VXmM|^*xuS5aeMxV@WBbH57M|s9of",
      "published_at": "2023-09-26T18:36:22.410000+00:00"
    }
  },
  {
    "id": 111178744395870924,
    "created_at": "2023-10-04T20:56:48.973000+00:00",
    "sensitive": false,
    "visibility": "public",
    "language": "cs",
    "uri": "https://mastodonczech.cz/users/honzajavorek/statuses/111178744395870924",
    "url": "https://mastodonczech.cz/@honzajavorek/111178744395870924",
    "replies_count": 1,
    "favourites_count": 3,
    "favourited": false,
    "reblogged": false,
    "muted": false,
    "bookmarked": false,
    "pinned": false,
    "content": "<p>Novo Nordisk je Dánská firma, která přišla s přípravkem proti cukrovce a obezitě. Je po něm obrovská poptávka a Novo je už hodnotnější než Coca-Cola. Jenže Dánsko je malá země pro takovou firmu a ekonomika státu se stává na úspěchu Novo Nordisk úplně závislá. <a href=\"https://www.thedial.world/issue-8/ozempic-novo-nordisk-denmark-economy\" target=\"_blank\" rel=\"nofollow noopener noreferrer\" translate=\"no\"><span class=\"invisible\">https://www.</span><span class=\"ellipsis\">thedial.world/issue-8/ozempic-</span><span class=\"invisible\">novo-nordisk-denmark-economy</span></a> <a href=\"https://mastodonczech.cz/tags/links\" class=\"mention hashtag\" rel=\"tag\">#<span>links</span></a></p>",
    "tags": [
      {
        "name": "links",
        "url": "https://mastodonczech.cz/tags/links"
      }
    ],
    "card": {
      "url": "https://www.thedial.world/issue-8/ozempic-novo-nordisk-denmark-economy",
      "title": "Ozempic's Economic Empire — The Dial",
      "description": "Novo Nordisk's success has created extraordinary opportunities for Denmark, but it might also be putting the country's economy at risk.",
      "language": "en",
      "type": "link",
      "provider_name": "The Dial",
      "width": 1500,
      "height": 788,
      "blurhash": "UZSFCEa}p{oKjZfQfkfQp_fQZgbHkCfQf6fQ"
    }
  },
  {
    "id": 111178493345571219,
    "created_at": "2023-10-04T19:52:58.319000+00:00",
    "sensitive": false,
    "visibility": "public",
    "language": "cs",
    "uri": "https://mastodonczech.cz/users/honzajavorek/statuses/111178493345571219",
    "url": "https://mastodonczech.cz/@honzajavorek/111178493345571219",
    "favourites_count": 1,
    "favourited": false,
    "reblogged": false,
    "muted": false,
    "bookmarked": false,
    "pinned": false,
    "content": "<p>„AI turns the marginal cost of content to zero. Whenever the marginal cost of something in the value chain is set to zero, this usually has a downstream effect on where distribution aggregates (e.g., the Internet turned the marginal cost of software distribution to zero).“ <a href=\"https://matt-rickard.com/is-ai-a-platform-shift\" target=\"_blank\" rel=\"nofollow noopener noreferrer\" translate=\"no\"><span class=\"invisible\">https://</span><span class=\"ellipsis\">matt-rickard.com/is-ai-a-platf</span><span class=\"invisible\">orm-shift</span></a> <a href=\"https://mastodonczech.cz/tags/links\" class=\"mention hashtag\" rel=\"tag\">#<span>links</span></a></p>",
    "tags": [
      {
        "name": "links",
        "url": "https://mastodonczech.cz/tags/links"
      }
    ],
    "card": {
      "url": "https://matt-rickard.com/is-ai-a-platform-shift",
      "title": "Is AI a Platform Shift?",
      "description": "You can think of a platform shift as a change in the dominant layer that applications are built on. It might look like Software > Hardware. Or Hardware > Software. A new layer becomes the dominant layer (e.g., most applications are being built on top of the new layer rather than the previous layer). As a result, the new layer might be able to capture the majority of the value from the previous generation (e.g., it might accrue the majority of the profits). New companies become dominant. New or d",
      "language": "en",
      "type": "link",
      "provider_name": "Matt Rickard",
      "width": 1200,
      "height": 630,
      "blurhash": "U74_tiWBM{ayayayj[fQ00ofxuj[ofj[ayj[",
      "published_at": "2023-09-29T13:30:38+00:00"
    }
  },
  {
    "id": 111178312642372491,
    "created_at": "2023-10-04T19:07:00.937000+00:00",
    "sensitive": false,
    "visibility": "public",
    "language": "cs",
    "uri": "https://mastodonczech.cz/users/honzajavorek/statuses/111178312642372491",
    "url": "https://mastodonczech.cz/@honzajavorek/111178312642372491",
    "favourites_count": 2,
    "favourited": false,
    "reblogged": false,
    "muted": false,
    "bookmarked": false,
    "pinned": false,
    "content": "<p>Mailová schránka po návratu z dovolené. Přesně takhle jsem to teď měl! <a href=\"https://nitter.cz/TomBorovsk1/status/1694042879780335751#m\" target=\"_blank\" rel=\"nofollow noopener noreferrer\" translate=\"no\"><span class=\"invisible\">https://</span><span class=\"ellipsis\">nitter.cz/TomBorovsk1/status/1</span><span class=\"invisible\">694042879780335751#m</span></a> <a href=\"https://mastodonczech.cz/tags/links\" class=\"mention hashtag\" rel=\"tag\">#<span>links</span></a></p>",
    "tags": [
      {
        "name": "links",
        "url": "https://mastodonczech.cz/tags/links"
      }
    ]
  },
  {
    "id": 111176475502650439,
    "created_at": "2023-10-04T11:19:48.409000+00:00",
    "sensitive": false,
    "visibility": "public",
    "language": "cs",
    "uri": "https://mastodonczech.cz/users/honzajavorek/statuses/111176475502650439",
    "url": "https://mastodonczech.cz/@honzajavorek/111176475502650439",
    "replies_count": 1,
    "favourites_count": 2,
    "favourited": false,
    "reblogged": false,
    "muted": false,
    "bookmarked": false,
    "pinned": false,
    "content": "<p>Udělejte si audit domácnosti a posviťte si na to, kdo kolik čeho dělá a jestli by to nešlo změnit tak, aby to bylo vyrovnanější. <a href=\"https://ferovadomacnost.cz/audit\" target=\"_blank\" rel=\"nofollow noopener noreferrer\" translate=\"no\"><span class=\"invisible\">https://</span><span class=\"\">ferovadomacnost.cz/audit</span><span class=\"invisible\"></span></a> <a href=\"https://mastodonczech.cz/tags/links\" class=\"mention hashtag\" rel=\"tag\">#<span>links</span></a></p>",
    "tags": [
      {
        "name": "links",
        "url": "https://mastodonczech.cz/tags/links"
      }
    ],
    "card": {
      "url": "https://ferovadomacnost.cz/audit",
      "title": "Audit domácnosti",
      "description": "Zjisti, jak na tom doma jste s dělbou práce a péče. Začni pomalu a jistě věci měnit tak, aby to bylo fér.",
      "language": "cs",
      "type": "link",
      "width": 1200,
      "height": 772,
      "blurhash": "UJCFhl#84:FxwJxuNGIU0yoz%LV@ELWB$*t7"
    }
  },
  {
    "id": 111155821649385657,
    "created_at": "2023-09-30T19:47:15.634000+00:00",
    "sensitive": false,
    "visibility": "public",
    "language": "cs",
    "uri": "https://mastodonczech.cz/users/honzajavorek/statuses/111155821649385657",
    "url": "https://mastodonczech.cz/@honzajavorek/111155821649385657",
    "reblogs_count": 2,
    "favourites_count": 2,
    "favourited": false,
    "reblogged": false,
    "muted": false,
    "bookmarked": false,
    "pinned": false,
    "content": "<p>Chcete si doma hrát se Stable Diffusion? Začněte tady. <a href=\"https://docs.google.com/presentation/d/1HEcE3qOAGVujcDaNQbiLXyx7zwKHQkXEILsYBhsot7A/edit\" target=\"_blank\" rel=\"nofollow noopener noreferrer\" translate=\"no\"><span class=\"invisible\">https://</span><span class=\"ellipsis\">docs.google.com/presentation/d</span><span class=\"invisible\">/1HEcE3qOAGVujcDaNQbiLXyx7zwKHQkXEILsYBhsot7A/edit</span></a> <a href=\"https://mastodonczech.cz/tags/links\" class=\"mention hashtag\" rel=\"tag\">#<span>links</span></a></p>",
    "tags": [
      {
        "name": "links",
        "url": "https://mastodonczech.cz/tags/links"
      }
    ],
    "card": {
      "url": "https://docs.google.com/presentation/d/1HEcE3qOAGVujcDaNQbiLXyx7zwKHQkXEILsYBhsot7A/edit?usp=embed_facebook",
      "title": "Typed Visions - SDXL - September 2023",
      "description": "Typed.visions Decoding AI in Image Creation Typed.visions",
      "language": "cs",
      "type": "link",
      "provider_name": "Google Docs",
      "width": 1200,
      "height": 630,
      "blurhash": "UC7^}Xt7M{t7IUayofay00RjxuRj?bofRjof"
    }
  },
  {
    "id": 111136828153438107,
    "created_at": "2023-09-27T11:16:57.872000+00:00",
    "sensitive": false,
    "visibility": "public",
    "language": "cs",
    "uri": "https://mastodonczech.cz/users/honzajavorek/statuses/111136828153438107",
    "url": "https://mastodonczech.cz/@honzajavorek/111136828153438107",
    "replies_count": 1,
    "favourited": false,
    "reblogged": false,
    "muted": false,
    "bookmarked": false,
    "pinned": false,
    "content": "<p>Soumrak předplatných a ekonomiky tvůrců? <a href=\"https://nickfthilton.medium.com/the-end-of-the-subscription-era-is-coming-ed197f252c6a\" target=\"_blank\" rel=\"nofollow noopener noreferrer\" translate=\"no\"><span class=\"invisible\">https://</span><span class=\"ellipsis\">nickfthilton.medium.com/the-en</span><span class=\"invisible\">d-of-the-subscription-era-is-coming-ed197f252c6a</span></a> <a href=\"https://mastodonczech.cz/tags/links\" class=\"mention hashtag\" rel=\"tag\">#<span>links</span></a></p>",
    "tags": [
      {
        "name": "links",
        "url": "https://mastodonczech.cz/tags/links"
      }
    ],
    "card": {
      "url": "https://nickfthilton.medium.com/the-end-of-the-subscription-era-is-coming-ed197f252c6a",
      "title": "The End of the Subscription Era is Coming - Nick Hilton - Medium",
      "description": "This piece exists thanks to the munificence of my paying newsletter subscribers. If you value you my writing on Medium, joining them is a great way to support that. I’m not just talking about…",
      "language": "en",
      "type": "link",
      "author_name": "Nick Hilton",
      "author_url": "https://nickfthilton.medium.com",
      "provider_name": "Medium",
      "width": 1200,
      "height": 755,
      "blurhash": "U7G[[{xu%MM{_3-;%M9F00?b-;9F_3ofxut7",
      "published_at": "2023-08-30T13:30:14.752000+00:00"
    }
  },
  {
    "id": 111115159897614467,
    "created_at": "2023-09-23T15:26:26.527000+00:00",
    "sensitive": false,
    "visibility": "public",
    "language": "cs",
    "uri": "https://mastodonczech.cz/users/honzajavorek/statuses/111115159897614467",
    "url": "https://mastodonczech.cz/@honzajavorek/111115159897614467",
    "replies_count": 3,
    "reblogs_count": 4,
    "favourites_count": 9,
    "favourited": false,
    "reblogged": false,
    "muted": false,
    "bookmarked": false,
    "pinned": false,
    "content": "<p>Neznal jsem. Borec z Londýna, který roky jezdí po světě vlakama a píše na web tipy jak na to. <a href=\"https://www.seat61.com/Czech.htm\" target=\"_blank\" rel=\"nofollow noopener noreferrer\" translate=\"no\"><span class=\"invisible\">https://www.</span><span class=\"\">seat61.com/Czech.htm</span><span class=\"invisible\"></span></a> <a href=\"https://mastodonczech.cz/tags/links\" class=\"mention hashtag\" rel=\"tag\">#<span>links</span></a></p>",
    "tags": [
      {
        "name": "links",
        "url": "https://mastodonczech.cz/tags/links"
      }
    ],
    "card": {
      "url": "https://www.seat61.com/Czech.htm",
      "title": "London to Prague by train | Times, fares, how to buy tickets",
      "description": "Train times, fares & how to buy tickets from London to Prague & Czechia by Eurostar and onward train.  UK to Prague without flying!",
      "language": "en",
      "type": "link"
    }
  },
  {
    "id": 111114338950829239,
    "created_at": "2023-09-23T11:57:39.878000+00:00",
    "sensitive": false,
    "visibility": "public",
    "language": "cs",
    "uri": "https://mastodonczech.cz/users/honzajavorek/statuses/111114338950829239",
    "url": "https://mastodonczech.cz/@honzajavorek/111114338950829239",
    "favourited": false,
    "reblogged": false,
    "muted": false,
    "bookmarked": false,
    "pinned": false,
    "content": "<p>„Penetruje a podmaní si opět jednoho dne klasika postmodernu?“ Fila o Elišce a Damiánovi. <a href=\"https://www.seznamzpravy.cz/clanek/kultura-eliska-a-damian-jako-nejhorsi-serial-vsech-dob-spis-slavnost-bezvyznamnosti-237176\" target=\"_blank\" rel=\"nofollow noopener noreferrer\" translate=\"no\"><span class=\"invisible\">https://www.</span><span class=\"ellipsis\">seznamzpravy.cz/clanek/kultura</span><span class=\"invisible\">-eliska-a-damian-jako-nejhorsi-serial-vsech-dob-spis-slavnost-bezvyznamnosti-237176</span></a> <a href=\"https://mastodonczech.cz/tags/links\" class=\"mention hashtag\" rel=\"tag\">#<span>links</span></a></p>",
    "tags": [
      {
        "name": "links",
        "url": "https://mastodonczech.cz/tags/links"
      }
    ],
    "card": {
      "url": "https://www.seznamzpravy.cz/clanek/kultura-eliska-a-damian-jako-nejhorsi-serial-vsech-dob-spis-slavnost-bezvyznamnosti-237176",
      "title": "Eliška a Damián jako nejhorší seriál všech dob? Spíš slavnost bezvýznamnosti",
      "description": "Proč budí televizní seriál s Emmou Smetanou tak silné reakce? Budete se divit, ale k jeho lepšímu pochopení je potřeba vzpomínat i na Pierra Bourdieua a Milana Kunderu. ",
      "language": "cs",
      "type": "link",
      "author_name": "Kamil Fila",
      "provider_name": "Seznam Zprávy",
      "width": 400,
      "height": 225,
      "blurhash": "UKDc2PR:9u?G%1oJM|xt0LV@xCIUE2WVxuRk"
    }
  },
  {
    "id": 111108269455066387,
    "created_at": "2023-09-22T10:14:06.840000+00:00",
    "sensitive": false,
    "visibility": "public",
    "language": "cs",
    "uri": "https://mastodonczech.cz/users/honzajavorek/statuses/111108269455066387",
    "url": "https://mastodonczech.cz/@honzajavorek/111108269455066387",
    "reblogs_count": 1,
    "favourites_count": 1,
    "edited_at": "2023-09-22T10:15:34.097000+00:00",
    "favourited": false,
    "reblogged": false,
    "muted": false,
    "bookmarked": false,
    "pinned": false,
    "content": "<p>Proč USA a Kanada téměř nemají MHD? Způsobila to složitá kombinace faktorů, která navíc byla v každém městě jiná. Na začátku soukromé monopoly provozující a ruinující MHD (mafie included), a potom 2. světová, po které nebyla Amerika zničená. Měli čas a peníze realizovat utopistické plány, tak všude postavili dálnice. <a href=\"https://overcast.fm/+LxR0R6OYQ\" target=\"_blank\" rel=\"nofollow noopener noreferrer\" translate=\"no\"><span class=\"invisible\">https://</span><span class=\"\">overcast.fm/+LxR0R6OYQ</span><span class=\"invisible\"></span></a> <a href=\"https://mastodonczech.cz/tags/links\" class=\"mention hashtag\" rel=\"tag\">#<span>links</span></a></p>",
    "tags": [
      {
        "name": "links",
        "url": "https://mastodonczech.cz/tags/links"
      }
    ],
    "card": {
      "url": "https://overcast.fm/+LxR0R6OYQ",
      "title": "AskHistorians Podcast Episode 212 – Public Transport in North America with Jake Berman — The AskHistorians Podcast",
      "description": "Jeremy Salkeld talks with Jake Berman about the development of public transport in the US and Canada, and the background to the US’ modern issues with urban transport infrastructure, including the rise and fall of the streetcar and difficulties with…",
      "language": "en",
      "type": "video",
      "html": "<iframe src=\"https://overcast.fm/podcasts/episode_card/828238347254148?t=0\" width=\"290\" height=\"58\" allowfullscreen=\"allowfullscreen\" scrolling=\"no\" frameborder=\"0\" sandbox=\"allow-scripts allow-same-origin allow-popups allow-popups-to-escape-sandbox allow-forms\"></iframe>",
      "width": 290,
      "height": 58,
      "embed_url": "https://traffic.libsyn.com/secure/askhistorians/AskHistorians_Pocast_Episode_212_-_American_Public_Transit_with_Jake_Berman.mp3?dest-id=172941#t=0",
      "blurhash": "UFR.$2nOUGcZnOi_bbXnUHjFm+jFofbbf7i_"
    }
  },
  {
    "id": 111035522652287065,
    "created_at": "2023-09-09T13:53:38.604000+00:00",
    "in_reply_to_id": null,
    "in_reply_to_account_id": null,
    "sensitive": false,
    "spoiler_text": "",
    "visibility": "public",
    "language": "cs",
    "uri": "https://mastodonczech.cz/users/honzajavorek/statuses/111035522652287065",
    "url": "https://mastodonczech.cz/@honzajavorek/111035522652287065",
    "replies_count": 0,
    "reblogs_count": 0,
    "favourites_count": 0,
    "edited_at": null,
    "favourited": false,
    "reblogged": false,
    "muted": false,
    "bookmarked": false,
    "pinned": false,
    "content": "<p>„Pokud si tedy odmítneme z koníčku udělat práci s tím, že by se z něj vytratila radost a spontánnost, je to jistě dobře, ale jde jen o začátek hlubší reflexe. Musíme se totiž sami sebe ptát i na to, proč a jak v nás vlastně díky koníčkům ona radost vzniká.“ <a href=\"https://www.seznamzpravy.cz/clanek/nazory-komentare-pod-carou-neni-nutne-mit-konicky-natoz-si-z-nich-delat-praci-236604\" target=\"_blank\" rel=\"nofollow noopener noreferrer\" translate=\"no\"><span class=\"invisible\">https://www.</span><span class=\"ellipsis\">seznamzpravy.cz/clanek/nazory-</span><span class=\"invisible\">komentare-pod-carou-neni-nutne-mit-konicky-natoz-si-z-nich-delat-praci-236604</span></a> <a href=\"https://mastodonczech.cz/tags/links\" class=\"mention hashtag\" rel=\"tag\">#<span>links</span></a></p>",
    "filtered": [],
    "reblog": null,
    "media_attachments": [],
    "mentions": [],
    "tags": [
      {
        "name": "links",
        "url": "https://mastodonczech.cz/tags/links"
      }
    ],
    "emojis": [],
    "card": {
      "url": "https://www.seznamzpravy.cz/clanek/nazory-komentare-pod-carou-neni-nutne-mit-konicky-natoz-si-z-nich-delat-praci-236604",
      "title": "Pod čarou: Není nutné mít koníčky. Natož si z nich dělat práci",
      "description": "Často se setkáváme s dobrými radami, jak bychom své koníčky měli změnit v práci snů. Dnešní Pod čarou proto zkoumá, co nás tlačí k proměně zábavy v zaměstnání, a jestli na celém konceptu koníčků nebylo něco špatně už odjakživa.",
      "language": "cs",
      "type": "link",
      "author_name": "Matouš Hrdina",
      "author_url": "",
      "provider_name": "Seznam Zprávy",
      "provider_url": "",
      "html": "",
      "width": 400,
      "height": 225,
      "image": null,
      "image_description": "",
      "embed_url": "",
      "blurhash": "UXQcJ4t7?aR*~oofIVWB?bWBRPoe0LafxtkC",
      "published_at": null
    },
    "poll": null
  }
]